<archimate:ArchimateDiagramModel
    xmlns:xsi="http://www.w3.org/2001/XMLSchema-instance"
    xmlns:archimate="http://www.archimatetool.com/archimate"
    name="OS.4. Управление обязательствами (НСУ)"
    id="48663cb5-8454-4168-9bfe-a663902b0b54">
  <children
      xsi:type="archimate:DiagramModelGroup"
      id="7d755434-f6dc-44cc-8fb9-1d7b48d4edd9"
      name="OS.4.Управление обязательствами (НСУ)              "
      textAlignment="1"
      fillColor="#fffff5"
      borderType="1">
    <bounds
        width="925"
        height="577"/>
    <children
        xsi:type="archimate:DiagramModelArchimateObject"
        id="ac3aa02b-2f97-4a1c-aa3e-2e5d53067b61"
        textPosition="1">
      <bounds
          x="72"
          y="36"
          width="217"
          height="67"/>
      <archimateElement
          xsi:type="archimate:BusinessProcess"
          href="BusinessProcess_00f4b6d8-fa34-4ed2-938d-212c28921892.xml#00f4b6d8-fa34-4ed2-938d-212c28921892"/>
    </children>
    <children
        xsi:type="archimate:DiagramModelArchimateObject"
        id="18c98b89-0e5e-41a3-843d-fb00491b38e8"
        textPosition="1">
      <bounds
          x="384"
          y="38"
          width="217"
          height="64"/>
      <archimateElement
          xsi:type="archimate:BusinessProcess"
          href="BusinessProcess_39c4b746-3064-41db-99cf-bdff4ca64381.xml#39c4b746-3064-41db-99cf-bdff4ca64381"/>
    </children>
    <children
        xsi:type="archimate:DiagramModelArchimateObject"
        id="1022b56a-c5fb-4aab-ac2c-3608f7586921"
        textPosition="1">
      <bounds
          x="696"
          y="38"
          width="217"
          height="64"/>
      <archimateElement
          xsi:type="archimate:BusinessProcess"
          href="BusinessProcess_12a9827f-2b6d-46f7-9ecb-caf9b9cfa074.xml#12a9827f-2b6d-46f7-9ecb-caf9b9cfa074"/>
    </children>
    <children
        xsi:type="archimate:DiagramModelArchimateObject"
        id="0c12c967-39ec-44e0-a738-2fdbe336d459"
        textAlignment="1"
        textPosition="1">
      <bounds
          x="12"
          y="132"
          width="253"
          height="49"/>
      <archimateElement
          xsi:type="archimate:BusinessProcess"
          href="BusinessProcess_dd76ae4f-cb65-40aa-a195-9f8d5cac0cae.xml#dd76ae4f-cb65-40aa-a195-9f8d5cac0cae"/>
    </children>
    <children
        xsi:type="archimate:DiagramModelArchimateObject"
        id="4ec44eff-033d-46aa-b485-0c1d9b32def2"
        textAlignment="1"
        textPosition="1">
      <bounds
          x="12"
          y="192"
          width="253"
          height="49"/>
      <archimateElement
          xsi:type="archimate:BusinessProcess"
          href="BusinessProcess_55170ff4-348e-4dab-9625-a9032dcb8db1.xml#55170ff4-348e-4dab-9625-a9032dcb8db1"/>
    </children>
    <children
        xsi:type="archimate:DiagramModelArchimateObject"
        id="05d7c491-9fcd-479d-b830-b371224fbd81"
        textAlignment="1"
        textPosition="1">
      <bounds
          x="12"
          y="252"
          width="253"
          height="49"/>
      <archimateElement
          xsi:type="archimate:BusinessProcess"
          href="BusinessProcess_a1f6b988-2206-4f89-8066-e252d26fcbc1.xml#a1f6b988-2206-4f89-8066-e252d26fcbc1"/>
    </children>
    <children
        xsi:type="archimate:DiagramModelArchimateObject"
        id="0c190963-b655-468e-8ba2-b1c4e585a196"
        textAlignment="1"
        textPosition="1">
      <bounds
          x="12"
          y="312"
          width="253"
          height="49"/>
      <archimateElement
          xsi:type="archimate:BusinessProcess"
          href="BusinessProcess_5a553c3b-9e41-4119-86d1-5e3e4fc2dae6.xml#5a553c3b-9e41-4119-86d1-5e3e4fc2dae6"/>
    </children>
    <children
        xsi:type="archimate:DiagramModelArchimateObject"
        id="a287c266-a5dc-4902-ab40-fbaaaae7d0a3"
        textAlignment="1"
        textPosition="1">
      <bounds
          x="324"
          y="132"
          width="253"
          height="49"/>
      <archimateElement
          xsi:type="archimate:BusinessProcess"
          href="BusinessProcess_970c023f-701f-489a-b0fd-f63ead3554b8.xml#970c023f-701f-489a-b0fd-f63ead3554b8"/>
    </children>
    <children
        xsi:type="archimate:DiagramModelArchimateObject"
        id="64a15fb2-abd4-4eff-a969-06f0a6690020"
        textAlignment="1"
        textPosition="1">
      <bounds
          x="324"
          y="192"
          width="253"
          height="49"/>
      <archimateElement
          xsi:type="archimate:BusinessProcess"
          href="BusinessProcess_c9d79d3e-966f-4c45-b7d6-7fe333b49c4e.xml#c9d79d3e-966f-4c45-b7d6-7fe333b49c4e"/>
    </children>
    <children
        xsi:type="archimate:DiagramModelArchimateObject"
        id="ff0578a6-05fc-427a-9655-e0c3a5fa35ec"
        textAlignment="1"
        textPosition="1">
      <bounds
          x="324"
          y="252"
          width="253"
          height="49"/>
      <archimateElement
          xsi:type="archimate:BusinessProcess"
          href="BusinessProcess_1fd4a991-9cc9-4aee-8244-a25a552e93c2.xml#1fd4a991-9cc9-4aee-8244-a25a552e93c2"/>
    </children>
    <children
        xsi:type="archimate:DiagramModelArchimateObject"
        id="afcd2bbc-be0b-499d-b64e-dc2ab509101f"
        textAlignment="1"
        textPosition="1">
      <bounds
          x="636"
          y="132"
          width="253"
          height="49"/>
      <archimateElement
          xsi:type="archimate:BusinessProcess"
          href="BusinessProcess_86829b46-50a0-4211-9d68-bb10d2878a6b.xml#86829b46-50a0-4211-9d68-bb10d2878a6b"/>
    </children>
    <children
        xsi:type="archimate:DiagramModelArchimateObject"
        id="0c05d0f4-1ac8-46d5-80b4-28ba00df252d"
        textAlignment="1"
        textPosition="1">
      <bounds
          x="636"
          y="192"
          width="253"
          height="61"/>
      <archimateElement
          xsi:type="archimate:BusinessProcess"
          href="BusinessProcess_ea7e5be1-60e1-4a85-a196-c16b0dc0119d.xml#ea7e5be1-60e1-4a85-a196-c16b0dc0119d"/>
    </children>
    <children
        xsi:type="archimate:DiagramModelArchimateObject"
        id="38fbe7d5-b71c-4a76-a712-cb85d11696d7"
        textAlignment="1"
        textPosition="1">
      <bounds
          x="636"
          y="264"
          width="253"
          height="49"/>
      <archimateElement
          xsi:type="archimate:BusinessProcess"
          href="BusinessProcess_d0a569c8-87a6-49f5-8dc1-3d382f177f91.xml#d0a569c8-87a6-49f5-8dc1-3d382f177f91"/>
    </children>
    <children
        xsi:type="archimate:DiagramModelArchimateObject"
        id="2b93aa94-b61c-4290-ae2f-8d719c7845e8"
        textAlignment="1"
        textPosition="1">
      <bounds
          x="636"
          y="324"
          width="253"
          height="49"/>
      <archimateElement
          xsi:type="archimate:BusinessProcess"
          href="BusinessProcess_60f7f22a-5e6f-4650-bb35-8086ef82e4dd.xml#60f7f22a-5e6f-4650-bb35-8086ef82e4dd"/>
    </children>
    <children
        xsi:type="archimate:DiagramModelArchimateObject"
        id="582888bf-c0f5-41c3-8c5a-8dfb51bef37e"
        textAlignment="1"
        textPosition="1">
      <bounds
          x="636"
          y="384"
          width="253"
          height="49"/>
      <archimateElement
          xsi:type="archimate:BusinessProcess"
          href="BusinessProcess_f43b83a7-8b07-4279-b885-e6ac749e510a.xml#f43b83a7-8b07-4279-b885-e6ac749e510a"/>
    </children>
    <children
        xsi:type="archimate:DiagramModelArchimateObject"
        id="de11e3a8-758b-4565-851d-3d763b7fd574"
        textAlignment="1"
        textPosition="1">
      <bounds
          x="636"
          y="444"
          width="253"
          height="61"/>
      <archimateElement
          xsi:type="archimate:BusinessProcess"
          href="BusinessProcess_44e1bb4a-30c1-4d51-87f1-3ba3c677d2a8.xml#44e1bb4a-30c1-4d51-87f1-3ba3c677d2a8"/>
    </children>
    <children
        xsi:type="archimate:DiagramModelArchimateObject"
        id="713ef550-3df1-4ced-be93-bbbc0a5d6b1c"
        textAlignment="1"
        textPosition="1">
      <bounds
          x="636"
          y="516"
          width="253"
          height="49"/>
      <archimateElement
          xsi:type="archimate:BusinessProcess"
          href="BusinessProcess_14dbc4e9-e72d-422b-bb2a-e5d3dbb944d9.xml#14dbc4e9-e72d-422b-bb2a-e5d3dbb944d9"/>
    </children>
  </children>
</archimate:ArchimateDiagramModel>
