<archimate:ArchimateDiagramModel
    xmlns:xsi="http://www.w3.org/2001/XMLSchema-instance"
    xmlns:archimate="http://www.archimatetool.com/archimate"
    name="OGP.4. Добыча углеводородов"
    id="a05a0493-1d8b-4670-beba-b88a88039fab">
  <children
      xsi:type="archimate:DiagramModelGroup"
      id="607cc027-6557-425a-b291-5418edfca0ca"
      name="OGP.4 . Добыча углеводородов                           "
      textAlignment="1"
      fillColor="#fffff4">
    <bounds
        x="-24"
        y="-24"
        width="1849"
        height="661"/>
    <children
        xsi:type="archimate:DiagramModelArchimateObject"
        id="18c579aa-afb4-4c5a-a480-a8a5cdcfb552"
        textPosition="1">
      <bounds
          x="48"
          y="48"
          width="193"
          height="61"/>
      <archimateElement
          xsi:type="archimate:BusinessProcess"
          href="BusinessProcess_0750e8d7-394b-4d5d-ae41-4fa4bef0a032.xml#0750e8d7-394b-4d5d-ae41-4fa4bef0a032"/>
    </children>
    <children
        xsi:type="archimate:DiagramModelArchimateObject"
        id="e761c0fa-d97e-48d4-9fb1-3a0d31a6a2df"
        textPosition="1">
      <bounds
          x="300"
          y="48"
          width="193"
          height="61"/>
      <archimateElement
          xsi:type="archimate:BusinessProcess"
          href="BusinessProcess_08a43428-3441-46ec-9dda-eb7be9996edc.xml#08a43428-3441-46ec-9dda-eb7be9996edc"/>
    </children>
    <children
        xsi:type="archimate:DiagramModelArchimateObject"
        id="84e6e6f2-5281-48bc-80cf-2667d656a036"
        textPosition="1">
      <bounds
          x="564"
          y="48"
          width="193"
          height="61"/>
      <archimateElement
          xsi:type="archimate:BusinessProcess"
          href="BusinessProcess_fb619830-52b4-4759-a760-ce0788ebea13.xml#fb619830-52b4-4759-a760-ce0788ebea13"/>
    </children>
    <children
        xsi:type="archimate:DiagramModelArchimateObject"
        id="5ec8df73-b03a-433f-ab71-b3ef38e2f0c6"
        textPosition="1">
      <bounds
          x="828"
          y="48"
          width="193"
          height="61"/>
      <archimateElement
          xsi:type="archimate:BusinessProcess"
          href="BusinessProcess_052ed5e2-75d1-4ecc-9da2-3d4a18a04fa2.xml#052ed5e2-75d1-4ecc-9da2-3d4a18a04fa2"/>
    </children>
    <children
        xsi:type="archimate:DiagramModelArchimateObject"
        id="9bb3fb08-7106-4823-b0ae-64ca832e4058"
        textPosition="1">
      <bounds
          x="1104"
          y="48"
          width="193"
          height="61"/>
      <archimateElement
          xsi:type="archimate:BusinessProcess"
          href="BusinessProcess_767dcf66-5002-4db0-a5e5-e369fdf087a0.xml#767dcf66-5002-4db0-a5e5-e369fdf087a0"/>
    </children>
    <children
        xsi:type="archimate:DiagramModelArchimateObject"
        id="8b1867df-f853-4577-be07-c186472fbdf8"
        textPosition="1">
      <bounds
          x="1368"
          y="48"
          width="193"
          height="61"/>
      <archimateElement
          xsi:type="archimate:BusinessProcess"
          href="BusinessProcess_82c9597a-e917-4a0c-9b26-47fa71b101a4.xml#82c9597a-e917-4a0c-9b26-47fa71b101a4"/>
    </children>
    <children
        xsi:type="archimate:DiagramModelArchimateObject"
        id="b6c62e84-c2ca-455e-a5cc-a210f7d39860"
        textAlignment="1"
        textPosition="1">
      <bounds
          x="12"
          y="144"
          width="205"
          height="61"/>
      <archimateElement
          xsi:type="archimate:BusinessProcess"
          href="BusinessProcess_7d158821-1cfd-45ed-84dd-03dca3c00639.xml#7d158821-1cfd-45ed-84dd-03dca3c00639"/>
    </children>
    <children
        xsi:type="archimate:DiagramModelArchimateObject"
        id="30f92d7c-9585-482f-ac1e-2a97c66d5a49"
        textAlignment="1"
        textPosition="1">
      <bounds
          x="12"
          y="216"
          width="205"
          height="49"/>
      <archimateElement
          xsi:type="archimate:BusinessProcess"
          href="BusinessProcess_2ecf39be-de19-40b5-9f6c-e338906b35af.xml#2ecf39be-de19-40b5-9f6c-e338906b35af"/>
    </children>
    <children
        xsi:type="archimate:DiagramModelArchimateObject"
        id="938e80e6-f639-4776-b3a0-94959388ee4a"
        textAlignment="1"
        textPosition="1">
      <bounds
          x="12"
          y="276"
          width="205"
          height="49"/>
      <archimateElement
          xsi:type="archimate:BusinessProcess"
          href="BusinessProcess_b1e3cbc2-ac12-4c65-a842-5d6dc8081264.xml#b1e3cbc2-ac12-4c65-a842-5d6dc8081264"/>
    </children>
    <children
        xsi:type="archimate:DiagramModelArchimateObject"
        id="e62b51e2-eada-4e9e-8c70-c78750be2751"
        textAlignment="1"
        textPosition="1">
      <bounds
          x="264"
          y="141"
          width="205"
          height="61"/>
      <archimateElement
          xsi:type="archimate:BusinessProcess"
          href="BusinessProcess_ef5d4ae7-b1d6-4e14-a497-aa8e5f80ceb6.xml#ef5d4ae7-b1d6-4e14-a497-aa8e5f80ceb6"/>
    </children>
    <children
        xsi:type="archimate:DiagramModelArchimateObject"
        id="25c6cd15-d81f-4e36-b22e-341971950144"
        textAlignment="1"
        textPosition="1">
      <bounds
          x="264"
          y="210"
          width="205"
          height="61"/>
      <archimateElement
          xsi:type="archimate:BusinessProcess"
          href="BusinessProcess_1d3634da-a27a-42df-afeb-dcb7274f4a4a.xml#1d3634da-a27a-42df-afeb-dcb7274f4a4a"/>
    </children>
    <children
        xsi:type="archimate:DiagramModelArchimateObject"
        id="17b6675c-619d-43aa-95a5-e0b96f04e748"
        textAlignment="1"
        textPosition="1">
      <bounds
          x="264"
          y="288"
          width="205"
          height="49"/>
      <archimateElement
          xsi:type="archimate:BusinessProcess"
          href="BusinessProcess_b0cf05fb-6c48-4658-9838-9b02f320c6ae.xml#b0cf05fb-6c48-4658-9838-9b02f320c6ae"/>
    </children>
    <children
        xsi:type="archimate:DiagramModelArchimateObject"
        id="5d3c6fe6-c277-43bc-bf93-b68d147f6556"
        textAlignment="1"
        textPosition="1">
      <bounds
          x="264"
          y="348"
          width="205"
          height="73"/>
      <archimateElement
          xsi:type="archimate:BusinessProcess"
          href="BusinessProcess_8bcf4f17-8a6c-46c5-96d3-fd69e8f469ae.xml#8bcf4f17-8a6c-46c5-96d3-fd69e8f469ae"/>
    </children>
    <children
        xsi:type="archimate:DiagramModelArchimateObject"
        id="079b8cf4-18d5-4df7-b2af-2a5b8b5ecff8"
        textAlignment="1"
        textPosition="1">
      <bounds
          x="528"
          y="147"
          width="205"
          height="55"/>
      <archimateElement
          xsi:type="archimate:BusinessProcess"
          href="BusinessProcess_799dfb2f-39bc-42cc-8ac0-171a78bdc8a2.xml#799dfb2f-39bc-42cc-8ac0-171a78bdc8a2"/>
    </children>
    <children
        xsi:type="archimate:DiagramModelArchimateObject"
        id="19190e16-5282-491a-87cc-3ab35aefa939"
        textAlignment="1"
        textPosition="1">
      <bounds
          x="528"
          y="210"
          width="205"
          height="49"/>
      <archimateElement
          xsi:type="archimate:BusinessProcess"
          href="BusinessProcess_9934f290-33bb-4ba2-838a-4da268164999.xml#9934f290-33bb-4ba2-838a-4da268164999"/>
    </children>
    <children
        xsi:type="archimate:DiagramModelArchimateObject"
        id="84067f70-5fc8-4ee6-9816-ece2a81e8c6f"
        textAlignment="1"
        textPosition="1">
      <bounds
          x="528"
          y="270"
          width="205"
          height="49"/>
      <archimateElement
          xsi:type="archimate:BusinessProcess"
          href="BusinessProcess_fef5fc06-5963-485f-aab0-8352e2684b64.xml#fef5fc06-5963-485f-aab0-8352e2684b64"/>
    </children>
    <children
        xsi:type="archimate:DiagramModelArchimateObject"
        id="a87a665a-15e7-44a2-9ca1-ffcb32b0e810"
        textAlignment="1"
        textPosition="1">
      <bounds
          x="528"
          y="336"
          width="205"
          height="97"/>
      <archimateElement
          xsi:type="archimate:BusinessProcess"
          href="BusinessProcess_436bb37a-c73f-4b0c-abdc-837e96b85edb.xml#436bb37a-c73f-4b0c-abdc-837e96b85edb"/>
    </children>
    <children
        xsi:type="archimate:DiagramModelArchimateObject"
        id="c82be84b-59a2-4721-921a-84b566ff970b"
        textPosition="1">
      <bounds
          x="1632"
          y="48"
          width="193"
          height="61"/>
      <archimateElement
          xsi:type="archimate:BusinessProcess"
          href="BusinessProcess_6824057b-6da3-45e4-bec6-964483f8e9bc.xml#6824057b-6da3-45e4-bec6-964483f8e9bc"/>
    </children>
    <children
        xsi:type="archimate:DiagramModelArchimateObject"
        id="f6d28495-88b3-4024-9c85-2959bd5a7d1a"
        textAlignment="1"
        textPosition="1">
      <bounds
          x="792"
          y="147"
          width="205"
          height="73"/>
      <archimateElement
          xsi:type="archimate:BusinessProcess"
          href="BusinessProcess_71ad1003-c770-4071-b336-7d44f58b7f0b.xml#71ad1003-c770-4071-b336-7d44f58b7f0b"/>
    </children>
    <children
        xsi:type="archimate:DiagramModelArchimateObject"
        id="4df79de1-178d-483c-8dee-bfa41b0bf880"
        textAlignment="1"
        textPosition="1">
      <bounds
          x="792"
          y="228"
          width="205"
          height="61"/>
      <archimateElement
          xsi:type="archimate:BusinessProcess"
          href="BusinessProcess_28259acd-d249-48c6-8c33-ac2e9ff16c85.xml#28259acd-d249-48c6-8c33-ac2e9ff16c85"/>
    </children>
    <children
        xsi:type="archimate:DiagramModelArchimateObject"
        id="3685d6d4-a8e1-4b4a-a272-a91ca99e2373"
        textAlignment="1"
        textPosition="1">
      <bounds
          x="792"
          y="300"
          width="205"
          height="121"/>
      <archimateElement
          xsi:type="archimate:BusinessProcess"
          href="BusinessProcess_480ec32f-a0ce-472a-964b-d87f11e7d6ee.xml#480ec32f-a0ce-472a-964b-d87f11e7d6ee"/>
    </children>
    <children
        xsi:type="archimate:DiagramModelArchimateObject"
        id="6fc3a0d0-6172-4ff0-b35e-82f6f2fe7ef3"
        textAlignment="1"
        textPosition="1">
      <bounds
          x="1056"
          y="146"
          width="205"
          height="58"/>
      <archimateElement
          xsi:type="archimate:BusinessProcess"
          href="BusinessProcess_785f8f1e-9e86-469e-84eb-73d27ea0a179.xml#785f8f1e-9e86-469e-84eb-73d27ea0a179"/>
    </children>
    <children
        xsi:type="archimate:DiagramModelArchimateObject"
        id="94365757-5696-4666-a16c-e77223f9244b"
        textAlignment="1"
        textPosition="1">
      <bounds
          x="1056"
          y="210"
          width="205"
          height="61"/>
      <archimateElement
          xsi:type="archimate:BusinessProcess"
          href="BusinessProcess_0ca054d2-0311-459b-bab1-a96a63644ef1.xml#0ca054d2-0311-459b-bab1-a96a63644ef1"/>
    </children>
    <children
        xsi:type="archimate:DiagramModelArchimateObject"
        id="a783ebfd-af6b-4291-b26c-77a32bf0a8db"
        textAlignment="1"
        textPosition="1">
      <bounds
          x="1056"
          y="282"
          width="205"
          height="61"/>
      <archimateElement
          xsi:type="archimate:BusinessProcess"
          href="BusinessProcess_6ff75908-b586-4d0d-9c7b-6718222efb98.xml#6ff75908-b586-4d0d-9c7b-6718222efb98"/>
    </children>
    <children
        xsi:type="archimate:DiagramModelArchimateObject"
        id="09d6b527-a2b0-46ed-9e38-394c76c81120"
        textAlignment="1"
        textPosition="1">
      <bounds
          x="1056"
          y="354"
          width="205"
          height="61"/>
      <archimateElement
          xsi:type="archimate:BusinessProcess"
          href="BusinessProcess_3d314549-47dd-40f4-b2b5-7d50a0bf1ed9.xml#3d314549-47dd-40f4-b2b5-7d50a0bf1ed9"/>
    </children>
    <children
        xsi:type="archimate:DiagramModelArchimateObject"
        id="02b5ab3d-4b1d-45ab-a424-bb9edbe4fe2d"
        textAlignment="1"
        textPosition="1">
      <bounds
          x="1056"
          y="432"
          width="205"
          height="121"/>
      <archimateElement
          xsi:type="archimate:BusinessProcess"
          href="BusinessProcess_4d116d31-8bb5-4528-bf8d-c8ae4b6746bf.xml#4d116d31-8bb5-4528-bf8d-c8ae4b6746bf"/>
    </children>
    <children
        xsi:type="archimate:DiagramModelArchimateObject"
        id="5fe43761-8842-44e6-ace5-b7ebf902fd48"
        textAlignment="1"
        textPosition="1">
      <bounds
          x="1056"
          y="564"
          width="205"
          height="73"/>
      <archimateElement
          xsi:type="archimate:BusinessProcess"
          href="BusinessProcess_8961a837-f38e-4346-aa59-96cd44e4a309.xml#8961a837-f38e-4346-aa59-96cd44e4a309"/>
    </children>
    <children
        xsi:type="archimate:DiagramModelArchimateObject"
        id="f0167e4a-c546-428e-b58d-df8297fd55ad"
        textAlignment="1"
        textPosition="1">
      <bounds
          x="1320"
          y="147"
          width="205"
          height="109"/>
      <archimateElement
          xsi:type="archimate:BusinessProcess"
          href="BusinessProcess_9592743a-509b-4983-a0d3-dfe7f864e01f.xml#9592743a-509b-4983-a0d3-dfe7f864e01f"/>
    </children>
    <children
        xsi:type="archimate:DiagramModelArchimateObject"
        id="915adedd-a082-45f8-9bc5-abf253be5241"
        textAlignment="1"
        textPosition="1">
      <bounds
          x="1320"
          y="264"
          width="205"
          height="109"/>
      <archimateElement
          xsi:type="archimate:BusinessProcess"
          href="BusinessProcess_77858e41-d2b8-4391-9784-6dd395fe76db.xml#77858e41-d2b8-4391-9784-6dd395fe76db"/>
    </children>
    <children
        xsi:type="archimate:DiagramModelArchimateObject"
        id="d5c49d7a-3127-4932-a9a5-f87440634021"
        textAlignment="1"
        textPosition="1">
      <bounds
          x="1320"
          y="384"
          width="205"
          height="85"/>
      <archimateElement
          xsi:type="archimate:BusinessProcess"
          href="BusinessProcess_39427ee5-b1f3-402e-a04e-0e23a4b83a13.xml#39427ee5-b1f3-402e-a04e-0e23a4b83a13"/>
    </children>
    <children
        xsi:type="archimate:DiagramModelArchimateObject"
        id="62ded5f5-771b-488c-a82a-5cfc050f826b"
        textAlignment="1"
        textPosition="1">
      <bounds
          x="1320"
          y="480"
          width="205"
          height="73"/>
      <archimateElement
          xsi:type="archimate:BusinessProcess"
          href="BusinessProcess_56ceb440-dc5c-4c85-8b5f-11f9d70e6331.xml#56ceb440-dc5c-4c85-8b5f-11f9d70e6331"/>
    </children>
    <children
        xsi:type="archimate:DiagramModelArchimateObject"
        id="3cd30ccb-727f-4097-b532-19a18e72f505"
        textAlignment="1"
        textPosition="1">
      <bounds
          x="1584"
          y="147"
          width="205"
          height="97"/>
      <archimateElement
          xsi:type="archimate:BusinessProcess"
          href="BusinessProcess_0a09a818-a5d5-4d66-8a8c-6c7f95649706.xml#0a09a818-a5d5-4d66-8a8c-6c7f95649706"/>
    </children>
    <children
        xsi:type="archimate:DiagramModelArchimateObject"
        id="e8744250-499e-4027-9f86-7cfe7d97aba1"
        textAlignment="1"
        textPosition="1">
      <bounds
          x="1584"
          y="255"
          width="205"
          height="61"/>
      <archimateElement
          xsi:type="archimate:BusinessProcess"
          href="BusinessProcess_482ecd2f-4140-472f-948e-0892fbd4a010.xml#482ecd2f-4140-472f-948e-0892fbd4a010"/>
    </children>
    <children
        xsi:type="archimate:DiagramModelArchimateObject"
        id="2a01a07a-62e2-4696-9113-77c3d1dcc9c1"
        textAlignment="1"
        textPosition="1">
      <bounds
          x="1584"
          y="324"
          width="205"
          height="73"/>
      <archimateElement
          xsi:type="archimate:BusinessProcess"
          href="BusinessProcess_f7290b03-8e74-4b65-9444-f9af1685800e.xml#f7290b03-8e74-4b65-9444-f9af1685800e"/>
    </children>
  </children>
</archimate:ArchimateDiagramModel>
