<archimate:ArchimateDiagramModel
    xmlns:xsi="http://www.w3.org/2001/XMLSchema-instance"
    xmlns:archimate="http://www.archimatetool.com/archimate"
    name="OGP.1. Формирование плана разработки"
    id="10da9bad-c7a9-4a3b-a609-111b317eabb0">
  <children
      xsi:type="archimate:DiagramModelGroup"
      id="ca60d5ac-665d-4662-9623-73b787def20d"
      name="OGP.1. Формирование плана разработки"
      textAlignment="1"
      fillColor="#ffffff">
    <bounds
        y="-24"
        width="1153"
        height="565"/>
    <children
        xsi:type="archimate:DiagramModelArchimateObject"
        id="e20eb4dc-67ec-4a80-8b97-dda3d99000a9"
        textPosition="1">
      <bounds
          x="48"
          y="60"
          width="241"
          height="73"/>
      <archimateElement
          xsi:type="archimate:BusinessProcess"
          href="BusinessProcess_75bfbf7f-2200-4d9b-98e8-b1fe195ea2b6.xml#75bfbf7f-2200-4d9b-98e8-b1fe195ea2b6"/>
    </children>
    <children
        xsi:type="archimate:DiagramModelArchimateObject"
        id="96bdbfbf-6ab7-480d-a68a-2733939cc05e"
        textPosition="1">
      <bounds
          x="348"
          y="60"
          width="217"
          height="73"/>
      <archimateElement
          xsi:type="archimate:BusinessProcess"
          href="BusinessProcess_d36aba17-24fe-40d4-85ad-078191203d63.xml#d36aba17-24fe-40d4-85ad-078191203d63"/>
    </children>
    <children
        xsi:type="archimate:DiagramModelArchimateObject"
        id="3207be0b-d193-46a9-843c-8fbe0df613b8"
        textPosition="1">
      <bounds
          x="636"
          y="60"
          width="229"
          height="73"/>
      <archimateElement
          xsi:type="archimate:BusinessProcess"
          href="BusinessProcess_d7e96c79-c902-4502-9c89-f5e7aecf84d5.xml#d7e96c79-c902-4502-9c89-f5e7aecf84d5"/>
    </children>
    <children
        xsi:type="archimate:DiagramModelArchimateObject"
        id="cf02d2d1-4d11-4eb0-9d1d-4bbf9c16c79e"
        textPosition="1">
      <bounds
          x="936"
          y="60"
          width="205"
          height="73"/>
      <archimateElement
          xsi:type="archimate:BusinessProcess"
          href="BusinessProcess_3e380d6a-df43-4e92-9a52-3090bf666135.xml#3e380d6a-df43-4e92-9a52-3090bf666135"/>
    </children>
    <children
        xsi:type="archimate:DiagramModelArchimateObject"
        id="928e69c8-920c-4350-895d-73a01bf9b787"
        textAlignment="1"
        textPosition="1">
      <bounds
          x="12"
          y="168"
          width="253"
          height="61"/>
      <archimateElement
          xsi:type="archimate:BusinessProcess"
          href="BusinessProcess_7fec56ad-2241-496f-81b6-be3504a6022e.xml#7fec56ad-2241-496f-81b6-be3504a6022e"/>
    </children>
    <children
        xsi:type="archimate:DiagramModelArchimateObject"
        id="db0f0cb9-6fce-4518-aa93-a7432ad50fc8"
        textAlignment="1"
        textPosition="1">
      <bounds
          x="12"
          y="252"
          width="253"
          height="49"/>
      <archimateElement
          xsi:type="archimate:BusinessProcess"
          href="BusinessProcess_df2034ee-4384-4536-b2bf-d5a3aba19fef.xml#df2034ee-4384-4536-b2bf-d5a3aba19fef"/>
    </children>
    <children
        xsi:type="archimate:DiagramModelArchimateObject"
        id="29358459-7b4c-49ee-b08d-96194b5c5b71"
        textAlignment="1"
        textPosition="1">
      <bounds
          x="12"
          y="324"
          width="253"
          height="61"/>
      <archimateElement
          xsi:type="archimate:BusinessProcess"
          href="BusinessProcess_5cebed0c-1393-4076-93c2-a83f2bccc92a.xml#5cebed0c-1393-4076-93c2-a83f2bccc92a"/>
    </children>
    <children
        xsi:type="archimate:DiagramModelArchimateObject"
        id="52dd70f6-575d-4a27-8c75-f55b5dc8ba11"
        textAlignment="1"
        textPosition="1">
      <bounds
          x="308"
          y="168"
          width="238"
          height="73"/>
      <archimateElement
          xsi:type="archimate:BusinessProcess"
          href="BusinessProcess_e4e1f59c-e8e3-4939-b28f-7082f9fbffdb.xml#e4e1f59c-e8e3-4939-b28f-7082f9fbffdb"/>
    </children>
    <children
        xsi:type="archimate:DiagramModelArchimateObject"
        id="9ce83bf9-6751-46b6-8b75-1a2968a268ee"
        textAlignment="1"
        textPosition="1">
      <bounds
          x="308"
          y="264"
          width="238"
          height="49"/>
      <archimateElement
          xsi:type="archimate:BusinessProcess"
          href="BusinessProcess_3dae1fb6-2e2f-4d12-bcec-e345b8b687cb.xml#3dae1fb6-2e2f-4d12-bcec-e345b8b687cb"/>
    </children>
    <children
        xsi:type="archimate:DiagramModelArchimateObject"
        id="4dc9e7c5-5568-4470-a195-e32e4d337674"
        textAlignment="1"
        textPosition="1">
      <bounds
          x="308"
          y="336"
          width="238"
          height="73"/>
      <archimateElement
          xsi:type="archimate:BusinessProcess"
          href="BusinessProcess_0caf1811-15d4-42ef-87e8-9baf601a0620.xml#0caf1811-15d4-42ef-87e8-9baf601a0620"/>
    </children>
    <children
        xsi:type="archimate:DiagramModelArchimateObject"
        id="9963c51c-0b13-4a34-8fc2-43d0e42cef36"
        textAlignment="1"
        textPosition="1">
      <bounds
          x="600"
          y="168"
          width="238"
          height="61"/>
      <archimateElement
          xsi:type="archimate:BusinessProcess"
          href="BusinessProcess_bd0c9826-0e3b-42fa-92c0-254b94233d8c.xml#bd0c9826-0e3b-42fa-92c0-254b94233d8c"/>
    </children>
    <children
        xsi:type="archimate:DiagramModelArchimateObject"
        id="f5d951c4-789a-4590-b352-08d78abab4c8"
        textAlignment="1"
        textPosition="1">
      <bounds
          x="600"
          y="240"
          width="238"
          height="61"/>
      <archimateElement
          xsi:type="archimate:BusinessProcess"
          href="BusinessProcess_da0903d2-01f6-4e5f-ae72-246d8ba9458b.xml#da0903d2-01f6-4e5f-ae72-246d8ba9458b"/>
    </children>
    <children
        xsi:type="archimate:DiagramModelArchimateObject"
        id="1ed2a2af-32a0-43fb-b0bf-e8f8ad3fc75e"
        textAlignment="1"
        textPosition="1">
      <bounds
          x="600"
          y="312"
          width="238"
          height="61"/>
      <archimateElement
          xsi:type="archimate:BusinessProcess"
          href="BusinessProcess_fc90e5dc-fb17-4855-ad23-7dcf8517cb50.xml#fc90e5dc-fb17-4855-ad23-7dcf8517cb50"/>
    </children>
    <children
        xsi:type="archimate:DiagramModelArchimateObject"
        id="3e9ca1cf-788b-41d4-8217-4ad3c4d58e03"
        textAlignment="1"
        textPosition="1">
      <bounds
          x="600"
          y="384"
          width="238"
          height="73"/>
      <archimateElement
          xsi:type="archimate:BusinessProcess"
          href="BusinessProcess_81e50190-7680-4dd3-b22f-18bb4e1ba0e3.xml#81e50190-7680-4dd3-b22f-18bb4e1ba0e3"/>
    </children>
    <children
        xsi:type="archimate:DiagramModelArchimateObject"
        id="e88dfcfd-2678-473f-ab55-7a0b26410488"
        textAlignment="1"
        textPosition="1">
      <bounds
          x="600"
          y="468"
          width="238"
          height="61"/>
      <archimateElement
          xsi:type="archimate:BusinessProcess"
          href="BusinessProcess_a42f286d-e9cc-4b82-a28d-c10f01ec9dc7.xml#a42f286d-e9cc-4b82-a28d-c10f01ec9dc7"/>
    </children>
    <children
        xsi:type="archimate:DiagramModelArchimateObject"
        id="0037e91e-e5fe-48b8-841b-84fe1ecf1354"
        textAlignment="1"
        textPosition="1">
      <bounds
          x="888"
          y="168"
          width="229"
          height="49"/>
      <archimateElement
          xsi:type="archimate:BusinessProcess"
          href="BusinessProcess_24dc80ce-77f8-4ed8-acc3-5fd061ef2372.xml#24dc80ce-77f8-4ed8-acc3-5fd061ef2372"/>
    </children>
    <children
        xsi:type="archimate:DiagramModelArchimateObject"
        id="2f7c7e7e-4618-4db6-922f-c3ba0770048c"
        textAlignment="1"
        textPosition="1">
      <bounds
          x="888"
          y="228"
          width="229"
          height="61"/>
      <archimateElement
          xsi:type="archimate:BusinessProcess"
          href="BusinessProcess_4f729c13-23c5-486c-8bef-f43070472333.xml#4f729c13-23c5-486c-8bef-f43070472333"/>
    </children>
    <children
        xsi:type="archimate:DiagramModelArchimateObject"
        id="41334e17-3161-4975-bcda-9d10184bd517"
        textAlignment="1"
        textPosition="1">
      <bounds
          x="888"
          y="300"
          width="229"
          height="61"/>
      <archimateElement
          xsi:type="archimate:BusinessProcess"
          href="BusinessProcess_2cf9a366-156b-4fa5-8c52-abf97be9bc6d.xml#2cf9a366-156b-4fa5-8c52-abf97be9bc6d"/>
    </children>
    <children
        xsi:type="archimate:DiagramModelArchimateObject"
        id="e6e74776-1297-4d98-917f-de554976d8c3"
        textAlignment="1"
        textPosition="1">
      <bounds
          x="888"
          y="372"
          width="229"
          height="73"/>
      <archimateElement
          xsi:type="archimate:BusinessProcess"
          href="BusinessProcess_3f4e2d3c-2d41-4325-864c-a1f6fc0f3dee.xml#3f4e2d3c-2d41-4325-864c-a1f6fc0f3dee"/>
    </children>
    <children
        xsi:type="archimate:DiagramModelArchimateObject"
        id="e0975ea2-2a9a-492f-92dc-964b89917e44"
        textAlignment="1"
        textPosition="1">
      <bounds
          x="888"
          y="456"
          width="229"
          height="97"/>
      <archimateElement
          xsi:type="archimate:BusinessProcess"
          href="BusinessProcess_54d7d3e2-6810-4226-ab4b-e319e7a72a50.xml#54d7d3e2-6810-4226-ab4b-e319e7a72a50"/>
    </children>
  </children>
</archimate:ArchimateDiagramModel>
