<archimate:ArchimateDiagramModel
    xmlns:xsi="http://www.w3.org/2001/XMLSchema-instance"
    xmlns:archimate="http://www.archimatetool.com/archimate"
    name="EMG.Подразделения"
    id="514ea7b9-8ea6-403c-b7fe-945ed941a017">
  <children
      xsi:type="archimate:DiagramModelGroup"
      id="3ccf1521-ef19-40ec-b939-6053f981bf2a"
      name="Производственный план ЭМГ-ПР-105-01"
      textAlignment="1"
      fillColor="#ffffee">
    <bounds
        x="5"
        y="5"
        width="1021"
        height="1026"/>
    <children
        xsi:type="archimate:DiagramModelArchimateObject"
        id="80d5ad3e-4874-4cdc-af44-7c38f9c58ed9"
        targetConnections="2977ee31-d182-4b6b-acbf-d2589005eff5"
        textAlignment="1"
        textPosition="1">
      <bounds
          x="335"
          y="55"
          width="226"
          height="66"/>
      <archimateElement
          xsi:type="archimate:BusinessObject"
          href="BusinessObject_35069886-d5d2-4566-80f9-34b5d7e78b72.xml#35069886-d5d2-4566-80f9-34b5d7e78b72"/>
    </children>
    <children
        xsi:type="archimate:DiagramModelArchimateObject"
        id="e7bc3f39-fd8f-42f4-8d5f-c3f3e504f821"
        targetConnections="e454d07f-05df-4ad6-9b75-c1a70072b4f1 1795011d-4aab-4cfc-91c7-486e8c96eca3"
        textAlignment="1"
        textPosition="1">
      <bounds
          x="335"
          y="140"
          width="226"
          height="66"/>
      <archimateElement
          xsi:type="archimate:BusinessObject"
          href="BusinessObject_17d5dd27-0393-42da-89cd-632479f6a94b.xml#17d5dd27-0393-42da-89cd-632479f6a94b"/>
    </children>
    <children
        xsi:type="archimate:DiagramModelArchimateObject"
        id="8f6972ef-1e64-4269-a19f-977fc38e2cf0"
        targetConnections="dddce718-a56b-4f2c-b707-1a255a9110a6"
        textAlignment="1"
        textPosition="1">
      <bounds
          x="335"
          y="225"
          width="226"
          height="66"/>
      <archimateElement
          xsi:type="archimate:BusinessObject"
          href="BusinessObject_de01dae7-3917-4ffb-a843-31bb0202fe45.xml#de01dae7-3917-4ffb-a843-31bb0202fe45"/>
    </children>
    <children
        xsi:type="archimate:DiagramModelArchimateObject"
        id="9458eedf-9a96-41db-8c06-46a262dca58e"
        targetConnections="ce3306f2-6412-4920-a086-1af75eac562b"
        textAlignment="1"
        textPosition="1">
      <bounds
          x="335"
          y="300"
          width="226"
          height="66"/>
      <archimateElement
          xsi:type="archimate:BusinessObject"
          href="BusinessObject_b1cac479-0917-423f-9c70-11df3b268e1f.xml#b1cac479-0917-423f-9c70-11df3b268e1f"/>
    </children>
    <children
        xsi:type="archimate:DiagramModelArchimateObject"
        id="11e3791d-0397-4b08-995a-0547e7c5ccc7"
        targetConnections="1d904056-1638-4e35-aee0-bca9ef8c49de"
        textAlignment="1"
        textPosition="1">
      <bounds
          x="335"
          y="375"
          width="226"
          height="66"/>
      <archimateElement
          xsi:type="archimate:BusinessObject"
          href="BusinessObject_dea52655-143a-4ea5-8812-2fde19415647.xml#dea52655-143a-4ea5-8812-2fde19415647"/>
    </children>
    <children
        xsi:type="archimate:DiagramModelArchimateObject"
        id="f4b1038b-b1ac-452b-99e5-75ee6d349424"
        targetConnections="138f4a70-fe70-409f-ba69-3ab71d109d1b"
        textAlignment="1"
        textPosition="1">
      <bounds
          x="335"
          y="450"
          width="226"
          height="66"/>
      <archimateElement
          xsi:type="archimate:BusinessObject"
          href="BusinessObject_4a023aff-f4e9-4e58-8aee-b4ab613a8182.xml#4a023aff-f4e9-4e58-8aee-b4ab613a8182"/>
    </children>
    <children
        xsi:type="archimate:DiagramModelArchimateObject"
        id="0e4ed2aa-8763-4b82-9106-116f0b6fea5f"
        targetConnections="7d4c59f1-ca1a-4d3e-9932-452c2ed022b2"
        textAlignment="1"
        textPosition="1">
      <bounds
          x="335"
          y="525"
          width="226"
          height="66"/>
      <archimateElement
          xsi:type="archimate:BusinessObject"
          href="BusinessObject_ed0daff5-d357-4be6-9062-096d76382295.xml#ed0daff5-d357-4be6-9062-096d76382295"/>
    </children>
    <children
        xsi:type="archimate:DiagramModelArchimateObject"
        id="9d637ae0-5195-4a09-bf6a-920a16e46358"
        targetConnections="664379f4-73d4-495c-b82b-4b127daed26f"
        textAlignment="1"
        textPosition="1">
      <bounds
          x="335"
          y="600"
          width="226"
          height="66"/>
      <archimateElement
          xsi:type="archimate:BusinessObject"
          href="BusinessObject_eda96dd6-1e0b-4c75-a5de-ebdc12e439bd.xml#eda96dd6-1e0b-4c75-a5de-ebdc12e439bd"/>
    </children>
    <children
        xsi:type="archimate:DiagramModelArchimateObject"
        id="1668d8ec-1e66-4ec3-ac39-c04348613e67"
        targetConnections="3a07269d-a5cb-494c-969f-a7a6fd91a504"
        textAlignment="1"
        textPosition="1">
      <bounds
          x="335"
          y="680"
          width="226"
          height="66"/>
      <archimateElement
          xsi:type="archimate:BusinessObject"
          href="BusinessObject_a5920f40-169f-439a-8d7f-d165af9c3306.xml#a5920f40-169f-439a-8d7f-d165af9c3306"/>
    </children>
    <children
        xsi:type="archimate:DiagramModelArchimateObject"
        id="82bf4b36-7a4b-42bb-8093-a5f5ae09112f"
        targetConnections="831257e9-1ce9-4ec0-a078-ff63ded5a7d0"
        textAlignment="1"
        textPosition="1">
      <bounds
          x="335"
          y="755"
          width="226"
          height="66"/>
      <archimateElement
          xsi:type="archimate:BusinessObject"
          href="BusinessObject_ab413610-8732-4544-8fdc-fc3555f6b3d2.xml#ab413610-8732-4544-8fdc-fc3555f6b3d2"/>
    </children>
    <children
        xsi:type="archimate:DiagramModelArchimateObject"
        id="09e51f75-ebca-4115-9cb9-5633c6300774"
        targetConnections="18003843-29be-402d-85dd-77ad113faec1"
        textAlignment="1"
        textPosition="1">
      <bounds
          x="335"
          y="830"
          width="226"
          height="66"/>
      <archimateElement
          xsi:type="archimate:BusinessObject"
          href="BusinessObject_34648d30-ec7f-4c08-8640-8081266c24b2.xml#34648d30-ec7f-4c08-8640-8081266c24b2"/>
    </children>
    <children
        xsi:type="archimate:DiagramModelArchimateObject"
        id="87aa141a-4b2c-473d-a69f-3d62d788f16b"
        targetConnections="2b4bc10b-7c00-4f86-a9de-3953da4eeae9"
        textAlignment="1"
        textPosition="1">
      <bounds
          x="335"
          y="905"
          width="226"
          height="66"/>
      <archimateElement
          xsi:type="archimate:BusinessObject"
          href="BusinessObject_b4309125-b729-4da2-aef7-cf7edf45f68e.xml#b4309125-b729-4da2-aef7-cf7edf45f68e"/>
    </children>
    <children
        xsi:type="archimate:DiagramModelArchimateObject"
        id="56135113-62fb-4bd9-9552-327d064c9368">
      <sourceConnections
          xsi:type="archimate:DiagramModelArchimateConnection"
          id="e454d07f-05df-4ad6-9b75-c1a70072b4f1"
          source="56135113-62fb-4bd9-9552-327d064c9368"
          target="e7bc3f39-fd8f-42f4-8d5f-c3f3e504f821">
        <archimateRelationship
            xsi:type="archimate:AccessRelationship"
            href="AccessRelationship_ff5cc161-a443-4b4d-b23c-3e49e63c57c0.xml#ff5cc161-a443-4b4d-b23c-3e49e63c57c0"/>
      </sourceConnections>
      <bounds
          x="15"
          y="171"
          width="151"
          height="55"/>
      <archimateElement
          xsi:type="archimate:BusinessActor"
          href="BusinessActor_bb23f383-7355-4c54-ab95-0e11234a38ef.xml#bb23f383-7355-4c54-ab95-0e11234a38ef"/>
    </children>
    <children
        xsi:type="archimate:DiagramModelArchimateObject"
        id="f5303ce9-1a3b-47e5-b685-5dd777dd2b54">
      <sourceConnections
          xsi:type="archimate:DiagramModelArchimateConnection"
          id="1795011d-4aab-4cfc-91c7-486e8c96eca3"
          source="f5303ce9-1a3b-47e5-b685-5dd777dd2b54"
          target="e7bc3f39-fd8f-42f4-8d5f-c3f3e504f821">
        <archimateRelationship
            xsi:type="archimate:AccessRelationship"
            href="AccessRelationship_2cc1df44-c18c-4058-9a2d-4dcca16c9a02.xml#2cc1df44-c18c-4058-9a2d-4dcca16c9a02"/>
      </sourceConnections>
      <sourceConnections
          xsi:type="archimate:DiagramModelArchimateConnection"
          id="ce3306f2-6412-4920-a086-1af75eac562b"
          source="f5303ce9-1a3b-47e5-b685-5dd777dd2b54"
          target="9458eedf-9a96-41db-8c06-46a262dca58e">
        <archimateRelationship
            xsi:type="archimate:AccessRelationship"
            href="AccessRelationship_42257b8d-e7d9-4c95-9a7e-541af5d09442.xml#42257b8d-e7d9-4c95-9a7e-541af5d09442"/>
      </sourceConnections>
      <bounds
          x="15"
          y="290"
          width="151"
          height="55"/>
      <archimateElement
          xsi:type="archimate:BusinessActor"
          href="BusinessActor_e1064488-1f6c-40ab-9e0d-57fdab31801d.xml#e1064488-1f6c-40ab-9e0d-57fdab31801d"/>
    </children>
    <children
        xsi:type="archimate:DiagramModelArchimateObject"
        id="28f06bf1-4512-43ea-a4d0-69e3d802ebef">
      <sourceConnections
          xsi:type="archimate:DiagramModelArchimateConnection"
          id="2977ee31-d182-4b6b-acbf-d2589005eff5"
          source="28f06bf1-4512-43ea-a4d0-69e3d802ebef"
          target="80d5ad3e-4874-4cdc-af44-7c38f9c58ed9">
        <archimateRelationship
            xsi:type="archimate:AccessRelationship"
            href="AccessRelationship_90beadf6-35b0-44f8-adc3-e14da7891cc8.xml#90beadf6-35b0-44f8-adc3-e14da7891cc8"/>
      </sourceConnections>
      <sourceConnections
          xsi:type="archimate:DiagramModelArchimateConnection"
          id="dddce718-a56b-4f2c-b707-1a255a9110a6"
          source="28f06bf1-4512-43ea-a4d0-69e3d802ebef"
          target="8f6972ef-1e64-4269-a19f-977fc38e2cf0">
        <archimateRelationship
            xsi:type="archimate:AccessRelationship"
            href="AccessRelationship_ede93f49-8bfd-4720-b4cd-62a5dd15c737.xml#ede93f49-8bfd-4720-b4cd-62a5dd15c737"/>
      </sourceConnections>
      <sourceConnections
          xsi:type="archimate:DiagramModelArchimateConnection"
          id="1d904056-1638-4e35-aee0-bca9ef8c49de"
          source="28f06bf1-4512-43ea-a4d0-69e3d802ebef"
          target="11e3791d-0397-4b08-995a-0547e7c5ccc7">
        <archimateRelationship
            xsi:type="archimate:AccessRelationship"
            href="AccessRelationship_fd87f61f-02d3-4d55-96d3-d73a964931a5.xml#fd87f61f-02d3-4d55-96d3-d73a964931a5"/>
      </sourceConnections>
      <bounds
          x="15"
          y="75"
          width="151"
          height="55"/>
      <archimateElement
          xsi:type="archimate:BusinessActor"
          href="BusinessActor_e7880bfd-6d25-49a6-a6f9-d705757428ba.xml#e7880bfd-6d25-49a6-a6f9-d705757428ba"/>
    </children>
    <children
        xsi:type="archimate:DiagramModelArchimateObject"
        id="1ee110d0-6e78-4451-8311-5f76e0a5893d">
      <sourceConnections
          xsi:type="archimate:DiagramModelArchimateConnection"
          id="138f4a70-fe70-409f-ba69-3ab71d109d1b"
          source="1ee110d0-6e78-4451-8311-5f76e0a5893d"
          target="f4b1038b-b1ac-452b-99e5-75ee6d349424">
        <archimateRelationship
            xsi:type="archimate:AccessRelationship"
            href="AccessRelationship_b2b86d1f-c3c0-474c-a026-165b74f0eed7.xml#b2b86d1f-c3c0-474c-a026-165b74f0eed7"/>
      </sourceConnections>
      <sourceConnections
          xsi:type="archimate:DiagramModelArchimateConnection"
          id="831257e9-1ce9-4ec0-a078-ff63ded5a7d0"
          source="1ee110d0-6e78-4451-8311-5f76e0a5893d"
          target="82bf4b36-7a4b-42bb-8093-a5f5ae09112f">
        <archimateRelationship
            xsi:type="archimate:AccessRelationship"
            href="AccessRelationship_2e997fcd-404b-47d6-bcd9-9cc2f143a58c.xml#2e997fcd-404b-47d6-bcd9-9cc2f143a58c"/>
      </sourceConnections>
      <bounds
          x="15"
          y="450"
          width="151"
          height="76"/>
      <archimateElement
          xsi:type="archimate:BusinessActor"
          href="BusinessActor_c091723c-ad3e-437f-8782-ff78aec0c14c.xml#c091723c-ad3e-437f-8782-ff78aec0c14c"/>
    </children>
    <children
        xsi:type="archimate:DiagramModelArchimateObject"
        id="2c9c13b8-7057-429d-be6d-64f5805c7af5">
      <sourceConnections
          xsi:type="archimate:DiagramModelArchimateConnection"
          id="7d4c59f1-ca1a-4d3e-9932-452c2ed022b2"
          source="2c9c13b8-7057-429d-be6d-64f5805c7af5"
          target="0e4ed2aa-8763-4b82-9106-116f0b6fea5f">
        <archimateRelationship
            xsi:type="archimate:AccessRelationship"
            href="AccessRelationship_c366b6bc-6493-435f-815e-d153aa902473.xml#c366b6bc-6493-435f-815e-d153aa902473"/>
      </sourceConnections>
      <sourceConnections
          xsi:type="archimate:DiagramModelArchimateConnection"
          id="664379f4-73d4-495c-b82b-4b127daed26f"
          source="2c9c13b8-7057-429d-be6d-64f5805c7af5"
          target="9d637ae0-5195-4a09-bf6a-920a16e46358">
        <archimateRelationship
            xsi:type="archimate:AccessRelationship"
            href="AccessRelationship_817f1263-2425-4b39-b57b-f2848b3a841d.xml#817f1263-2425-4b39-b57b-f2848b3a841d"/>
      </sourceConnections>
      <bounds
          x="15"
          y="536"
          width="151"
          height="55"/>
      <archimateElement
          xsi:type="archimate:BusinessActor"
          href="BusinessActor_7e73dd07-93f0-4410-a2bd-1c0cd0876bdb.xml#7e73dd07-93f0-4410-a2bd-1c0cd0876bdb"/>
    </children>
    <children
        xsi:type="archimate:DiagramModelArchimateObject"
        id="0b46f7ef-c638-42ae-bb60-86611f17fea8">
      <sourceConnections
          xsi:type="archimate:DiagramModelArchimateConnection"
          id="3a07269d-a5cb-494c-969f-a7a6fd91a504"
          source="0b46f7ef-c638-42ae-bb60-86611f17fea8"
          target="1668d8ec-1e66-4ec3-ac39-c04348613e67">
        <archimateRelationship
            xsi:type="archimate:AccessRelationship"
            href="AccessRelationship_698d14b5-9a5a-42e5-a37a-4dac9e6e2bb2.xml#698d14b5-9a5a-42e5-a37a-4dac9e6e2bb2"/>
      </sourceConnections>
      <bounds
          x="15"
          y="685"
          width="151"
          height="86"/>
      <archimateElement
          xsi:type="archimate:BusinessActor"
          href="BusinessActor_ff208cc9-44ec-4ee0-9854-e2bc29ed260a.xml#ff208cc9-44ec-4ee0-9854-e2bc29ed260a"/>
    </children>
    <children
        xsi:type="archimate:DiagramModelArchimateObject"
        id="4526450b-3a4d-49a6-939e-4eb83d529c04">
      <sourceConnections
          xsi:type="archimate:DiagramModelArchimateConnection"
          id="18003843-29be-402d-85dd-77ad113faec1"
          source="4526450b-3a4d-49a6-939e-4eb83d529c04"
          target="09e51f75-ebca-4115-9cb9-5633c6300774">
        <archimateRelationship
            xsi:type="archimate:AccessRelationship"
            href="AccessRelationship_bebff231-ffb1-42f0-aeb6-88f0211fdef3.xml#bebff231-ffb1-42f0-aeb6-88f0211fdef3"/>
      </sourceConnections>
      <bounds
          x="15"
          y="835"
          width="151"
          height="55"/>
      <archimateElement
          xsi:type="archimate:BusinessActor"
          href="BusinessActor_a2f6f54d-5fef-47f3-8eba-6feb152ffd05.xml#a2f6f54d-5fef-47f3-8eba-6feb152ffd05"/>
    </children>
    <children
        xsi:type="archimate:DiagramModelArchimateObject"
        id="dad1c4ce-1fcc-49b0-bfae-c293d194e0d0">
      <sourceConnections
          xsi:type="archimate:DiagramModelArchimateConnection"
          id="2b4bc10b-7c00-4f86-a9de-3953da4eeae9"
          source="dad1c4ce-1fcc-49b0-bfae-c293d194e0d0"
          target="87aa141a-4b2c-473d-a69f-3d62d788f16b">
        <archimateRelationship
            xsi:type="archimate:AccessRelationship"
            href="AccessRelationship_5eb7cf09-b270-49f0-b6ea-5391e849f041.xml#5eb7cf09-b270-49f0-b6ea-5391e849f041"/>
      </sourceConnections>
      <bounds
          x="15"
          y="916"
          width="151"
          height="55"/>
      <archimateElement
          xsi:type="archimate:BusinessActor"
          href="BusinessActor_79699371-8ec8-4377-9b9a-ac3bc4f7dd23.xml#79699371-8ec8-4377-9b9a-ac3bc4f7dd23"/>
    </children>
  </children>
</archimate:ArchimateDiagramModel>
